skillnet/__init__.py
skillnet/ai_tasker.py
skillnet/human_agent.py
skillnet-1.0.3.dist-info/LICENSE
skillnet-1.0.3.dist-info/METADATA
skillnet-1.0.3.dist-info/WHEEL
skillnet-1.0.3.dist-info/top_level.txt
skillnet-1.0.3.dist-info/RECORD
