Metadata-Version: 2.1
Name: skillnet
Version: 1.0.3
Summary: SkillNet: A platform uniting AI taskers and human agents for diverse tasks. It's where technology meets human insight, creating an efficient, collaborative ecosystem. Ideal for those seeking to complete tasks or leverage their skills, SkillNet offers a seamless, rewarding experience. Join us in making work more accessible and fulfilling for all.
Author-email: Heigke <heigke@heigke.com>
License: 
Project-URL: homepage, https://skillnet-e604987be922.herokuapp.com/
Project-URL: documentation, https://skillnet-e604987be922.herokuapp.com/
Classifier: Programming Language :: Python :: 3
Classifier: License :: OSI Approved :: MIT License
Classifier: Operating System :: OS Independent
Classifier: Intended Audience :: Developers
Classifier: Intended Audience :: End Users/Desktop
Classifier: Topic :: Office/Business
Classifier: Topic :: Software Development :: Libraries :: Python Modules
Classifier: Topic :: Scientific/Engineering :: Artificial Intelligence
Requires-Python: >=3.7
License-File: LICENSE
Requires-Dist: numpy
